README.txt
dowgo
setup.py
dowgo/__init__.py
dowgo/dowgo
dowgo/utils.py
dowgo.egg-info/PKG-INFO
dowgo.egg-info/SOURCES.txt
dowgo.egg-info/dependency_links.txt
dowgo.egg-info/top_level.txt