Metadata-Version: 2.1
Name: dowgo
Version: 1.0.2
Summary: Just a simple package manager
Home-page: UNKNOWN
Author: NDRAEY
License: UNKNOWN
Platform: UNKNOWN
